{"wBepDZdnsVj+OqBgdQFawA==":"mbr.jpg","6tvZSxFfsRdU6pXqwZhJxg==":"mbr-1.jpg","YKT45cSs3YWxvYnFTdTJkQ==":"mbr-2.jpg","d/um4017aTz1NNofMy02dw==":"mbr-3.jpg","OSubyTzxakkdej/EDMh19A==":"mbr-4.jpg","bpomlyMxmAHQpttUpZhz5w==":"mbr-5.jpg","KnLH5lZFuec4Eb9+BLoDhQ==":"jesus%201.png-640x400.png","HaLNQnDM8u7Ab5jJWSKmvA==":"jesus2.png-640x400.png","D69e9nZgQej+DUh9Mgsz6w==":"jesus3.png-640x400.png","7xeprLGHCY5UBvSFllgSNg==":"jesusm2-900x500.jpg","Ybks3vToyw3XPtLmZJJ/Xg==":"jesusm3-1024x680.jpg","9IzEjP2RhVpelVUb0L8G3Q==":"jesusm5-560x338.jpg","dpi2/H2r6T8grX4vsn15vQ==":"jesusm6-271x186.jpg","5cm/UkXIHzjZ5sp9YkdepQ==":"jesusm1-1080x1080.jpg","8puNG05+zl2hcnk3rjIGXQ==":"dios%20no%20ha%20muerto,%20por%20julio%20benitez.gif","PgrUh+b3qqnG1lpZDdCLGw==":"dios%20no%20ha%20muerto,%20por%20julio%20benitez.png","kYOM6laS0w7oor4k0oG9CA==":"dios%20no%20ha%20muerto,%20por%20julio%20benitez.png"}